jokes_and_quotes/cli.py
jokes_and_quotes/jokes.json
jokes_and_quotes/quotes.json
jokes_and_quotes/utils.py
jokes_and_quotes-1.0.3.dist-info/LICENSE
jokes_and_quotes-1.0.3.dist-info/METADATA
jokes_and_quotes-1.0.3.dist-info/WHEEL
jokes_and_quotes-1.0.3.dist-info/entry_points.txt
jokes_and_quotes-1.0.3.dist-info/top_level.txt
jokes_and_quotes-1.0.3.dist-info/RECORD
